README.txt
idtech.py
setup.py
pyidtech.egg-info/PKG-INFO
pyidtech.egg-info/SOURCES.txt
pyidtech.egg-info/dependency_links.txt
pyidtech.egg-info/requires.txt
pyidtech.egg-info/top_level.txt