Metadata-Version: 1.0
Name: pyidtech
Version: 0.1
Summary: read data from ID TECH credit card readers
Home-page: https://github.com/eighthave/pyidtech
Author: Hans-Christoph Steiner
Author-email: hans@eds.org
License: PSF License
Platform: UNKNOWN
Classifier: Intended Audience :: Developers
Classifier: License :: OSI Approved :: Python Software Foundation License
Classifier: Programming Language :: Python :: 2
Classifier: Topic :: Software Development :: Libraries :: Python Modules
Classifier: Topic :: Office/Business :: Financial :: Point-Of-Sale
Classifier: Topic :: System :: Hardware
